anyrobo/__init__.py
anyrobo/assistant.py
anyrobo/cli.py
anyrobo-0.1.0.dist-info/licenses/LICENSE
anyrobo-0.1.0.dist-info/METADATA
anyrobo-0.1.0.dist-info/WHEEL
anyrobo-0.1.0.dist-info/entry_points.txt
anyrobo-0.1.0.dist-info/top_level.txt
anyrobo-0.1.0.dist-info/RECORD
