Metadata-Version: 2.4
Name: anyrobo
Version: 0.1.0
Summary: Create your own JARVIS or GLADOS: a framework for voice-powered AI assistants with unique personalities
Author-email: Viet-Anh Nguyen <vietanh.dev@gmail.com>
License: MIT
Project-URL: Homepage, https://github.com/vietanhdev/anyrobo
Project-URL: Bug Tracker, https://github.com/vietanhdev/anyrobo/issues
Classifier: Programming Language :: Python :: 3
Classifier: Programming Language :: Python :: 3.10
Classifier: Programming Language :: Python :: 3.11
Classifier: Programming Language :: Python :: 3.12
Classifier: License :: OSI Approved :: MIT License
Classifier: Operating System :: MacOS
Classifier: Topic :: Scientific/Engineering :: Artificial Intelligence
Classifier: Topic :: Multimedia :: Sound/Audio :: Speech
Requires-Python: >=3.10
License-File: LICENSE
Requires-Dist: numpy<3.0.0,>=2.0.0
Requires-Dist: onnxruntime<2.0.0,>=1.16.0
Requires-Dist: kokoro-onnx>=0.2.0
Requires-Dist: lightning-whisper-mlx<0.1.0,>=0.0.10
Requires-Dist: sounddevice<0.6.0,>=0.4.6
Requires-Dist: ollama<0.5.0,>=0.4.0
Dynamic: license-file
